example/divider.v
module divider_8bit (
    input  wire        clk,
    input  wire        rst,
    input  wire        start,
    input  wire [7:0]  dividend,
    input  wire [7:0]  divisor,

    output reg  [7:0]  quotient,
    output reg  [7:0]  remainder,
    output reg         busy,
    output reg         done
);

    // Registers
    reg [7:0] quotient_q;      // Q
    reg [7:0] divisor_q;       // D
    reg [8:0] remainder_q;     // R (1 bit rộng hơn để kiểm tra âm)
    reg [3:0] count;           // đếm 8 bước

    // Wires cho giá trị tiếp theo
    reg [7:0] quotient_next;
    reg [8:0] remainder_next;

    // -------------------------------------------------------------------
    // Combinational logic: tính toán R_next, Q_next
    // -------------------------------------------------------------------
    always @(*) begin
        quotient_next  = quotient_q;
        remainder_next = remainder_q;

        if (busy) begin
            // Step 1: shift (R,Q)
            remainder_next = {remainder_q[7:0], quotient_q[7]};
            quotient_next  = {quotient_q[6:0], 1'b0};

            // Step 2: subtract divisor
            remainder_next = remainder_next - {1'b0, divisor_q};

            // Step 3: check sign
            if (remainder_next[8]) begin
                // Nếu âm → restore
                remainder_next = remainder_next + {1'b0, divisor_q};
                quotient_next[0] = 1'b0;
            end else begin
                quotient_next[0] = 1'b1;
            end
        end
    end

    // -------------------------------------------------------------------
    // Sequential logic: cập nhật
    // -------------------------------------------------------------------
    always @(posedge clk or posedge rst) begin
        if (rst) begin
            quotient_q  <= 0;
            divisor_q   <= 0;
            remainder_q <= 0;
            quotient    <= 0;
            remainder   <= 0;
            count       <= 0;
            busy        <= 0;
            done        <= 0;
        end else if (start && !busy) begin
            if (divisor == 0) begin
                // Trường hợp chia cho 0
                quotient <= 8'hFF;   // hoặc báo lỗi
                remainder <= dividend;
                busy <= 0;
                done <= 1;
            end else begin
                // Khởi tạo
                quotient_q  <= dividend;
                divisor_q   <= divisor;
                remainder_q <= 0;
                count       <= 8;
                busy        <= 1;
                done        <= 0;
            end
        end else if (busy) begin
            quotient_q  <= quotient_next;
            remainder_q <= remainder_next;
            count       <= count - 1;

            if (count == 1) begin
                busy      <= 0;
                done      <= 1;
                quotient  <= quotient_next;
                remainder <= remainder_next[7:0];
            end
        end else begin
            done <= 0; // clear sau khi đọc xong
        end
    end

endmodule


`timescale 1ns/1ps

module divider_8bit_tb();

    // Định nghĩa các tín hiệu test
    reg         clk;
    reg         rst;
    reg         start;
    reg  [7:0]  dividend;
    reg  [7:0]  divisor;
    wire [7:0]  quotient;
    wire [7:0]  remainder;
    wire        busy;
    wire        done;

    // Khởi tạo DUT (Device Under Test)
    divider_8bit dut (
        .clk(clk),
        .rst(rst),
        .start(start),
        .dividend(dividend),
        .divisor(divisor),
        .quotient(quotient),
        .remainder(remainder),
        .busy(busy),
        .done(done)
    );

    // Tạo xung clock 100MHz (chu kỳ 10ns)
    always #5 clk = ~clk;

    // Task kiểm tra kết quả
    task check_division;
        input [7:0] div_in;    // Số bị chia
        input [7:0] div_by;    // Số chia
        input [7:0] exp_q;     // Thương số mong đợi
        input [7:0] exp_r;     // Số dư mong đợi
        begin
            @(posedge clk);
            start = 1;
            dividend = div_in;
            divisor = div_by;
            @(posedge clk);
            start = 0;
            
            // Đợi cho đến khi done=1
            wait(done);
            
            // Kiểm tra kết quả
            if (quotient !== exp_q || remainder !== exp_r) begin
                $display("Lỗi: %d/%d = %d dư %d (mong đợi %d dư %d)", 
                    div_in, div_by, quotient, remainder, exp_q, exp_r);
            end else begin
                $display("Đúng: %d/%d = %d dư %d", 
                    div_in, div_by, quotient, remainder);
            end
            
            @(posedge clk);
            wait(!done);  // Đợi done về 0
        end
    endtask

    // Test stimulus
    initial begin
        // Tạo file wave
        $dumpfile("divider_tb.vcd");
        $dumpvars(0, divider_8bit_tb);

        // Khởi tạo các tín hiệu
        clk = 0;
        rst = 1;
        start = 0;
        dividend = 0;
        divisor = 0;

        // Reset
        #100;
        rst = 0;
        #10;

        // Test case 1: 25/4 = 6 dư 1
        check_division(8'd25, 8'd4, 8'd6, 8'd1);

        // Test case 2: 255/2 = 127 dư 1
        check_division(8'd255, 8'd2, 8'd127, 8'd1);

        // Test case 3: 100/10 = 10 dư 0
        check_division(8'd100, 8'd10, 8'd10, 8'd0);

        // Test case 4: 7/9 = 0 dư 7
        check_division(8'd7, 8'd9, 8'd0, 8'd7);

        // Test case 5: Chia cho 0
        check_division(8'd123, 8'd0, 8'hFF, 8'd123);

        // Kết thúc test
        #100;
        $display("Hoàn thành tất cả test!");
        $finish;
    end

    // Monitor các thay đổi
    initial begin
        $monitor("Time=%0d rst=%b start=%b busy=%b done=%b dividend=%d divisor=%d q=%d r=%d",
            $time, rst, start, busy, done, dividend, divisor, quotient, remainder);
    end

endmodule

example/divider_tb.vcd
$date
	Sat Sep 06 20:26:28 2025
$end
$version
	Icarus Verilog
$end
$timescale
	1ps
$end
$scope module divider_8bit_tb $end
$var wire 8 ! remainder [7:0] $end
$var wire 8 " quotient [7:0] $end
$var wire 1 # done $end
$var wire 1 $ busy $end
$var reg 1 % clk $end
$var reg 8 & dividend [7:0] $end
$var reg 8 ' divisor [7:0] $end
$var reg 1 ( rst $end
$var reg 1 ) start $end
$scope module dut $end
$var wire 1 % clk $end
$var wire 8 * dividend [7:0] $end
$var wire 8 + divisor [7:0] $end
$var wire 1 ( rst $end
$var wire 1 ) start $end
$var reg 1 $ busy $end
$var reg 4 , count [3:0] $end
$var reg 8 - divisor_q [7:0] $end
$var reg 1 # done $end
$var reg 8 . quotient [7:0] $end
$var reg 8 / quotient_next [7:0] $end
$var reg 8 0 quotient_q [7:0] $end
$var reg 8 1 remainder [7:0] $end
$var reg 9 2 remainder_next [8:0] $end
$var reg 9 3 remainder_q [8:0] $end
$upscope $end
$scope task check_division $end
$var reg 8 4 div_by [7:0] $end
$var reg 8 5 div_in [7:0] $end
$var reg 8 6 exp_q [7:0] $end
$var reg 8 7 exp_r [7:0] $end
$upscope $end
$upscope $end
$enddefinitions $end
$comment Show the parameter values. $end
$dumpall
$end
#0
$dumpvars
bx 7
bx 6
bx 5
bx 4
b0 3
b0 2
b0 1
b0 0
b0 /
b0 .
b0 -
b0 ,
b0 +
b0 *
0)
1(
b0 '
b0 &
0%
0$
0#
b0 "
b0 !
$end
#5000
1%
#10000
0%
#15000
1%
#20000
0%
#25000
1%
#30000
0%
#35000
1%
#40000
0%
#45000
1%
#50000
0%
#55000
1%
#60000
0%
#65000
1%
#70000
0%
#75000
1%
#80000
0%
#85000
1%
#90000
0%
#95000
1%
#100000
0%
0(
#105000
1%
#110000
0%
b1 7
b110 6
b100 4
b11001 5
#115000
b0 2
b110010 /
1$
b1000 ,
b100 -
b11001 0
b100 '
b100 +
b11001 &
b11001 *
1)
1%
#120000
0%
#125000
b0 2
b1100100 /
b111 ,
b110010 0
0)
1%
#130000
0%
#135000
b0 2
b11001000 /
b110 ,
b1100100 0
1%
#140000
0%
#145000
b10010000 /
b1 2
b101 ,
b11001000 0
1%
#150000
0%
#155000
b100000 /
b11 2
b100 ,
b1 3
b10010000 0
1%
#160000
0%
#165000
b1000001 /
b10 2
b11 ,
b11 3
b100000 0
1%
#170000
0%
#175000
b10000011 /
b0 2
b10 ,
b10 3
b1000001 0
1%
#180000
0%
#185000
b110 /
b1 2
b1 ,
b0 3
b10000011 0
1%
#190000
0%
#195000
b1 !
b1 1
b110 "
b110 .
1#
0$
b0 ,
b1 3
b110 0
1%
#200000
0%
#205000
b1111111 6
b10 4
b11111111 5
0#
1%
#210000
0%
#215000
b1 2
b11111110 /
1$
b1000 ,
b0 3
b10 -
b11111111 0
b10 '
b10 +
b11111111 &
b11111111 *
1)
1%
#220000
0%
#225000
b11111101 /
b1 2
b111 ,
b1 3
b11111110 0
0)
1%
#230000
0%
#235000
b11111011 /
b1 2
b110 ,
b11111101 0
1%
#240000
0%
#245000
b11110111 /
b1 2
b101 ,
b11111011 0
1%
#250000
0%
#255000
b11101111 /
b1 2
b100 ,
b11110111 0
1%
#260000
0%
#265000
b11011111 /
b1 2
b11 ,
b11101111 0
1%
#270000
0%
#275000
b10111111 /
b1 2
b10 ,
b11011111 0
1%
#280000
0%
#285000
b1111111 /
b1 2
b1 ,
b10111111 0
1%
#290000
0%
#295000
b1111111 "
b1111111 .
1#
0$
b0 ,
b1111111 0
1%
#300000
0%
#305000
b0 7
b1010 6
b1010 4
b1100100 5
0#
1%
#310000
0%
#315000
b0 2
b11001000 /
1$
b1000 ,
b0 3
b1010 -
b1100100 0
b1010 '
b1010 +
b1100100 &
b1100100 *
1)
1%
#320000
0%
#325000
b10010000 /
b1 2
b111 ,
b11001000 0
0)
1%
#330000
0%
#335000
b100000 /
b11 2
b110 ,
b1 3
b10010000 0
1%
#340000
0%
#345000
b1000000 /
b110 2
b101 ,
b11 3
b100000 0
1%
#350000
0%
#355000
b10000001 /
b10 2
b100 ,
b110 3
b1000000 0
1%
#360000
0%
#365000
b10 /
b101 2
b11 ,
b10 3
b10000001 0
1%
#370000
0%
#375000
b101 /
b0 2
b10 ,
b101 3
b10 0
1%
#380000
0%
#385000
b0 2
b1010 /
b1 ,
b0 3
b101 0
1%
#390000
0%
#395000
b0 !
b0 1
b1010 "
b1010 .
1#
0$
b0 ,
b1010 0
1%
#400000
0%
#405000
b111 7
b0 6
b1001 4
b111 5
0#
1%
#410000
0%
#415000
b0 2
b1110 /
1$
b1000 ,
b1001 -
b111 0
b1001 '
b1001 +
b111 &
b111 *
1)
1%
#420000
0%
#425000
b0 2
b11100 /
b111 ,
b1110 0
0)
1%
#430000
0%
#435000
b0 2
b111000 /
b110 ,
b11100 0
1%
#440000
0%
#445000
b0 2
b1110000 /
b101 ,
b111000 0
1%
#450000
0%
#455000
b0 2
b11100000 /
b100 ,
b1110000 0
1%
#460000
0%
#465000
b11000000 /
b1 2
b11 ,
b11100000 0
1%
#470000
0%
#475000
b10000000 /
b11 2
b10 ,
b1 3
b11000000 0
1%
#480000
0%
#485000
b0 /
b111 2
b1 ,
b11 3
b10000000 0
1%
#490000
0%
#495000
b111 !
b111 1
b0 "
b0 .
1#
0$
b0 ,
b111 3
b0 0
1%
#500000
0%
#505000
b1111011 7
b11111111 6
b0 4
b1111011 5
0#
1%
#510000
0%
#515000
1#
b1111011 !
b1111011 1
b11111111 "
b11111111 .
b0 '
b0 +
b1111011 &
b1111011 *
1)
1%
#520000
0%
#525000
0#
0)
1%
