riscv_base_defines.v
// Định nghĩa macro trong ALU
`define ALU_NONE                        4'b0000
`define ALU_SHIFT_LEFT                  4'b0001
`define ALU_SHIFT_RIGHT                 4'b0010
`define ALU_SHIFT_RIGHT_ARITHMETIC      4'b0011
`define ALU_ADD                         4'b0100
`define ALU_SUB                         4'b0101
`define ALU_AND                         4'b0110
`define ALU_OR                          4'b0111
`define ALU_XOR                         4'b1000
`define ALU_LESS_THAN                   4'b1001
`define ALU_LESS_THAN_UNSIGNED          4'b1010

// Định nghĩa macro trong bộ NHÂN
//1. mul
// mul
`define INST_MUL 32'h2000033
`define INST_MUL_MASK 32'hfe00707f

//2. mulh
`define INST_MULH 32'h2001033
`define INST_MULH_MASK 32'hfe00707f

//3. mulhsu
`define INST_MULHSU 32'h2002033
`define INST_MULHSU_MASK 32'hfe00707f

//4. mulhu
`define INST_MULHU 32'h2003033
`define INST_MULHU_MASK 32'hfe00707f

// Định nghĩa macro trong bộ CHIA
//1. div
`define INST_DIV 32'h2004033
`define INST_DIV_MASK 32'hfe00707f

//2. divu
`define INST_DIVU 32'h2005033
`define INST_DIVU_MASK 32'hfe00707f

//3. rem
`define INST_REM 32'h2006033
`define INST_REM_MASK 32'hfe00707f

//4. remu
`define INST_REMU 32'h2007033
`define INST_REMU_MASK 32'hfe00707f

riscv_base_divider.v
module riscv_base_divider (
    input           clk_i,
    input           rst_i,
    input           opcode_valid_i,     // Báo hiệu lệnh đầu vào hợp lệ, bắt đầu chia
    input  [31:0]   opcode_opcode_i,    // Mã lệnh opcode
    input  [31:0]   opcode_pc_i,        // Địa chỉ lệnh hiện tại (Program Counter)
    input           opcode_invalid_i,   // Báo hiệu lệnh đầu vào không hợp lệ
    input  [4:0]    opcode_rd_idx_i,    // Chỉ số thanh ghi đích (rd)
    input  [4:0]    opcode_ra_idx_i,    // Chỉ số thanh ghi nguồn 1 (ra)
    input  [4:0]    opcode_rb_idx_i,    // Chỉ số thanh ghi nguồn 2 (rb)
    input  [31:0]   opcode_ra_operand_i,// Số bị chia (dividend)
    input  [31:0]   opcode_rb_operand_i,// Số chia (divisor)
    output          writeback_valid_o,  // Báo hiệu kết quả sẵn sàng
    output [31:0]   writeback_value_o   // Kết quả phép chia hoặc dư
);

    `include "riscv_base_defines.v"

    // ========== INSTRUCTION DECODING ==========
    wire inst_div_w  = (opcode_opcode_i & `INST_DIV_MASK) == `INST_DIV;    // Chia có dấu
    wire inst_divu_w = (opcode_opcode_i & `INST_DIVU_MASK) == `INST_DIVU;  // Chia không dấu
    wire inst_rem_w  = (opcode_opcode_i & `INST_REM_MASK) == `INST_REM;    // Dư có dấu
    wire inst_remu_w = (opcode_opcode_i & `INST_REMU_MASK) == `INST_REMU;  // Dư không dấu

    wire div_rem_inst_w = inst_div_w | inst_divu_w | inst_rem_w | inst_remu_w;
    wire signed_operation_w = inst_div_w | inst_rem_w;
    wire div_operation_w = inst_div_w | inst_divu_w;

    // ========== SPECIAL CASES DETECTION ==========
    wire div_by_zero_w = (opcode_rb_operand_i == 32'h0);
    wire overflow_w = signed_operation_w & 
                      (opcode_ra_operand_i == 32'h80000000) & 
                      (opcode_rb_operand_i == 32'hFFFFFFFF);

    // ========== CONTROL SIGNALS ==========
    wire valid_div_req_w = opcode_valid_i & div_rem_inst_w & ~opcode_invalid_i;
    wire div_start_w = valid_div_req_w & ~div_by_zero_w & ~overflow_w & ~div_busy_q;
    wire special_case_w = valid_div_req_w & (div_by_zero_w | overflow_w);
    wire div_complete_w = (cycle_counter_q == 5'd0) & div_busy_q;

    // ========== SIGN PROCESSING ==========
    wire dividend_negative_w = signed_operation_w & opcode_ra_operand_i[31];
    wire divisor_negative_w = signed_operation_w & opcode_rb_operand_i[31];
    wire result_negative_w = signed_operation_w & 
                             ((div_operation_w & (opcode_ra_operand_i[31] ^ opcode_rb_operand_i[31])) |
                              (~div_operation_w & opcode_ra_operand_i[31])); // REM takes sign of dividend

    // Two's complement conversion
    wire [31:0] dividend_abs_w = dividend_negative_w ? (~opcode_ra_operand_i + 1'b1) : opcode_ra_operand_i;
    wire [31:0] divisor_abs_w = divisor_negative_w ? (~opcode_rb_operand_i + 1'b1) : opcode_rb_operand_i;

    // ========== STATE REGISTERS ==========
    reg [31:0] remainder_q;     // Current remainder
    reg [31:0] quotient_q;      // Current quotient
    reg [31:0] divisor_q;       // Divisor (constant)
    reg [5:0]  cycle_counter_q; // Bit counter (32 down to 1)
    reg        div_busy_q;      // Division in progress
    reg        div_inst_q;      // 1=DIV/DIVU, 0=REM/REMU
    reg        invert_result_q; // Need to negate final result
    reg        valid_q;         // Output valid signal
    reg [31:0] result_q;        // Final result

    // ========== DIVISION BUSY FLAG ==========
    always @(posedge clk_i or posedge rst_i) begin
        if (rst_i) begin
            div_busy_q <= 1'b0;
        end else begin
            if (div_start_w) begin
                div_busy_q <= 1'b1;
            end else if (div_complete_w) begin
                div_busy_q <= 1'b0;
            end
        end
    end

    // ========== CYCLE COUNTER ==========
    always @(posedge clk_i or posedge rst_i) begin
        if (rst_i) begin
            cycle_counter_q <= 6'd0;
        end else begin
            if (div_start_w) begin
                cycle_counter_q <= 6'd32; // Count 32 cycles
            end else if (div_busy_q & (cycle_counter_q != 6'd0)) begin
                cycle_counter_q <= cycle_counter_q - 1'b1;
            end
        end
    end

    // ========== OPERATION TYPE REGISTER ==========
    always @(posedge clk_i or posedge rst_i) begin
        if (rst_i) begin
            div_inst_q <= 1'b0;
        end else begin
            if (div_start_w) begin
                div_inst_q <= div_operation_w;
            end
        end
    end

    // ========== RESULT SIGN REGISTER ==========
    always @(posedge clk_i or posedge rst_i) begin
        if (rst_i) begin
            invert_result_q <= 1'b0;
        end else begin
            if (div_start_w) begin
                invert_result_q <= result_negative_w & |opcode_rb_operand_i;
            end
        end
    end

    // ========== DIVISOR REGISTER ==========
    always @(posedge clk_i or posedge rst_i) begin
        if (rst_i) begin
            divisor_q <= 32'h0;
        end else begin
            if (div_start_w) begin
                divisor_q <= divisor_abs_w;
            end
        end
    end

    // ========== RESTORING DIVISION ALGORITHM ==========
    always @(posedge clk_i or posedge rst_i) begin
        if (rst_i) begin
            remainder_q <= 32'h0;
            quotient_q <= 32'h0;
        end else begin
            if (div_start_w) begin
                remainder_q <= 32'h0;
                quotient_q <= dividend_abs_w;  // Load dividend into quotient initially
            end else if (div_busy_q & (cycle_counter_q != 5'd0)) begin
                // Shift remainder and quotient left
                remainder_q <= {remainder_q[30:0], quotient_q[31]};
                quotient_q <= quotient_q << 1;
                
                // Try subtraction
                if ({1'b0, remainder_q[30:0], quotient_q[31]} >= {1'b0, divisor_q}) begin
                    remainder_q <= {remainder_q[30:0], quotient_q[31]} - divisor_q;
                    quotient_q[0] <= 1'b1;  // Set LSB of quotient
                end else begin
                    quotient_q[0] <= 1'b0;  // Clear LSB of quotient
                end
            end
        end
    end

    // ========== OUTPUT VALID FLAG ==========
    always @(posedge clk_i or posedge rst_i) begin
        if (rst_i) begin
            valid_q <= 1'b0;
        end else begin
            if (div_complete_w | special_case_w) begin
                valid_q <= 1'b1;
            end else if (valid_q & ~opcode_valid_i) begin
                valid_q <= 1'b0;
            end
        end
    end

    // ========== RESULT CALCULATION ==========
    wire [31:0] final_quotient_w = invert_result_q ? (~quotient_q + 1'b1) : quotient_q;
    wire [31:0] final_remainder_w = invert_result_q ? (~remainder_q + 1'b1) : remainder_q;

    always @(posedge clk_i or posedge rst_i) begin
        if (rst_i) begin
            result_q <= 32'h0;
        end else begin
            if (div_complete_w) begin
                result_q <= div_inst_q ? final_quotient_w : final_remainder_w;
            end else if (special_case_w) begin
                if (div_by_zero_w) begin
                    result_q <= div_operation_w ? 32'hFFFFFFFF : opcode_ra_operand_i;
                end else if (overflow_w) begin
                    result_q <= div_operation_w ? 32'h80000000 : 32'h0;
                end
            end
        end
    end

    // ========== OUTPUT ASSIGNMENTS ==========
    assign writeback_valid_o = valid_q;
    assign writeback_value_o = result_q;

endmodule

riscv_base_divider_tb.v
`timescale 1ns / 1ps

`include "riscv_base_defines.v"
`include "riscv_base_divider.v"


module riscv_base_divider_tb;
    // ========== TESTBENCH SIGNALS ==========
    reg         clk_i;
    reg         rst_i;
    reg         opcode_valid_i;
    reg [31:0]  opcode_opcode_i;
    reg [31:0]  opcode_pc_i;
    reg         opcode_invalid_i;
    reg [4:0]   opcode_rd_idx_i;
    reg [4:0]   opcode_ra_idx_i;
    reg [4:0]   opcode_rb_idx_i;
    reg [31:0]  opcode_ra_operand_i;
    reg [31:0]  opcode_rb_operand_i;
    
    wire        writeback_valid_o;
    wire [31:0] writeback_value_o;

    // ========== TEST VARIABLES ==========
    integer test_count;
    integer pass_count;
    integer fail_count;
    reg [31:0] expected_result;
    reg [200*8-1:0] test_name;

    // ========== CLOCK GENERATION ==========
    initial begin
        clk_i = 0;
        forever #5 clk_i = ~clk_i; // 100MHz clock
    end

    // ========== DUT INSTANTIATION ==========
    riscv_base_divider dut (
        .clk_i              (clk_i),
        .rst_i              (rst_i),
        .opcode_valid_i     (opcode_valid_i),
        .opcode_opcode_i    (opcode_opcode_i),
        .opcode_pc_i        (opcode_pc_i),
        .opcode_invalid_i   (opcode_invalid_i),
        .opcode_rd_idx_i    (opcode_rd_idx_i),
        .opcode_ra_idx_i    (opcode_ra_idx_i),
        .opcode_rb_idx_i    (opcode_rb_idx_i),
        .opcode_ra_operand_i(opcode_ra_operand_i),
        .opcode_rb_operand_i(opcode_rb_operand_i),
        .writeback_valid_o  (writeback_valid_o),
        .writeback_value_o  (writeback_value_o)
    );

    // ========== TASK: RESET SYSTEM ==========
    task reset_system;
        begin
            rst_i = 1;
            opcode_valid_i = 0;
            opcode_opcode_i = 0;
            opcode_pc_i = 0;
            opcode_invalid_i = 0;
            opcode_rd_idx_i = 0;
            opcode_ra_idx_i = 0;
            opcode_rb_idx_i = 0;
            opcode_ra_operand_i = 0;
            opcode_rb_operand_i = 0;
            repeat(3) @(posedge clk_i);
            rst_i = 0;
            repeat(2) @(posedge clk_i);
        end
    endtask

    // ========== TASK: EXECUTE DIVISION ==========
    task execute_division(
        input [31:0] opcode,
        input [31:0] dividend,
        input [31:0] divisor,
        input [31:0] expected,
        input [200*8-1:0] name
    );
        begin
            test_name = name;
            expected_result = expected;
            
            // Setup instruction
            opcode_valid_i = 1;
            opcode_opcode_i = opcode;
            opcode_pc_i = 32'h1000;
            opcode_invalid_i = 0;
            opcode_rd_idx_i = 5'd1;
            opcode_ra_idx_i = 5'd2;
            opcode_rb_idx_i = 5'd3;
            opcode_ra_operand_i = dividend;
            opcode_rb_operand_i = divisor;

            @(posedge clk_i);
            opcode_valid_i = 0; // Only valid for 1 cycle

            // Wait for completion
            wait(writeback_valid_o);
            @(posedge clk_i);
            
            // Check result
            check_result();
            
            // Clear valid signal
            repeat(2) @(posedge clk_i);
        end
    endtask

    // ========== TASK: CHECK RESULT ==========
    task check_result;
        begin
            test_count = test_count + 1;
            if (writeback_value_o == expected_result) begin
                $display("[PASS] Test %0d: %s", test_count, test_name);
                $display("       Dividend: %0d (0x%08h), Divisor: %0d (0x%08h)", 
                        $signed(opcode_ra_operand_i), opcode_ra_operand_i,
                        $signed(opcode_rb_operand_i), opcode_rb_operand_i);
                $display("       Expected: %0d (0x%08h), Got: %0d (0x%08h)", 
                        $signed(expected_result), expected_result,
                        $signed(writeback_value_o), writeback_value_o);
                pass_count = pass_count + 1;
            end else begin
                $display("[FAIL] Test %0d: %s", test_count, test_name);
                $display("       Dividend: %0d (0x%08h), Divisor: %0d (0x%08h)", 
                        $signed(opcode_ra_operand_i), opcode_ra_operand_i,
                        $signed(opcode_rb_operand_i), opcode_rb_operand_i);
                $display("       Expected: %0d (0x%08h), Got: %0d (0x%08h)", 
                        $signed(expected_result), expected_result,
                        $signed(writeback_value_o), writeback_value_o);
                fail_count = fail_count + 1;
            end
            $display("");
        end
    endtask

    // ========== MAIN TEST SEQUENCE ==========
    initial begin
        $display("========================================");
        $display("RISC-V Base Divider Testbench Starting");
        $display("========================================");
        
        test_count = 0;
        pass_count = 0;
        fail_count = 0;
        
        reset_system();

        // ========== BASIC DIV TESTS ==========
        $display("Testing DIV (signed division)...");
        execute_division(`INST_DIV, 32'd20, 32'd3, 32'd6, "DIV: 20 / 3 = 6");
        execute_division(`INST_DIV, 32'd100, 32'd10, 32'd10, "DIV: 100 / 10 = 10");
        execute_division(`INST_DIV, 32'd1, 32'd1, 32'd1, "DIV: 1 / 1 = 1");
        execute_division(`INST_DIV, -32'd20, 32'd3, -32'd6, "DIV: -20 / 3 = -6");
        execute_division(`INST_DIV, 32'd20, -32'd3, -32'd6, "DIV: 20 / -3 = -6");
        execute_division(`INST_DIV, -32'd20, -32'd3, 32'd6, "DIV: -20 / -3 = 6");
        
        // ========== BASIC DIVU TESTS ==========
        $display("Testing DIVU (unsigned division)...");
        execute_division(`INST_DIVU, 32'd20, 32'd3, 32'd6, "DIVU: 20 / 3 = 6");
        execute_division(`INST_DIVU, 32'hFFFFFFFF, 32'd2, 32'h7FFFFFFF, "DIVU: 0xFFFFFFFF / 2 = 0x7FFFFFFF");
        execute_division(`INST_DIVU, 32'h80000000, 32'd2, 32'h40000000, "DIVU: 0x80000000 / 2 = 0x40000000");
        
        // ========== BASIC REM TESTS ==========
        $display("Testing REM (signed remainder)...");
        execute_division(`INST_REM, 32'd20, 32'd3, 32'd2, "REM: 20 % 3 = 2");
        execute_division(`INST_REM, 32'd100, 32'd10, 32'd0, "REM: 100 % 10 = 0");
        execute_division(`INST_REM, -32'd20, 32'd3, -32'd2, "REM: -20 % 3 = -2");
        execute_division(`INST_REM, 32'd20, -32'd3, 32'd2, "REM: 20 % -3 = 2");
        execute_division(`INST_REM, -32'd20, -32'd3, -32'd2, "REM: -20 % -3 = -2");
        
        // ========== BASIC REMU TESTS ==========
        $display("Testing REMU (unsigned remainder)...");
        execute_division(`INST_REMU, 32'd20, 32'd3, 32'd2, "REMU: 20 % 3 = 2");
        execute_division(`INST_REMU, 32'hFFFFFFFF, 32'd2, 32'd1, "REMU: 0xFFFFFFFF % 2 = 1");
        execute_division(`INST_REMU, 32'h80000001, 32'd2, 32'd1, "REMU: 0x80000001 % 2 = 1");
        
        // ========== DIVIDE BY ZERO TESTS ==========
        $display("Testing divide by zero cases...");
        execute_division(`INST_DIV, 32'd10, 32'd0, 32'hFFFFFFFF, "DIV: 10 / 0 = -1");
        execute_division(`INST_DIVU, 32'd10, 32'd0, 32'hFFFFFFFF, "DIVU: 10 / 0 = -1");
        execute_division(`INST_REM, 32'd10, 32'd0, 32'd10, "REM: 10 % 0 = 10");
        execute_division(`INST_REMU, 32'd10, 32'd0, 32'd10, "REMU: 10 % 0 = 10");
        
        // ========== OVERFLOW TESTS ==========
        $display("Testing overflow cases...");
        execute_division(`INST_DIV, 32'h80000000, 32'hFFFFFFFF, 32'h80000000, "DIV: -2147483648 / -1 = -2147483648 (overflow)");
        execute_division(`INST_REM, 32'h80000000, 32'hFFFFFFFF, 32'h0, "REM: -2147483648 % -1 = 0 (overflow)");
        
        // ========== EDGE CASES ==========
        $display("Testing edge cases...");
        execute_division(`INST_DIV, 32'd0, 32'd5, 32'd0, "DIV: 0 / 5 = 0");
        execute_division(`INST_DIVU, 32'd0, 32'd5, 32'd0, "DIVU: 0 / 5 = 0");
        execute_division(`INST_REM, 32'd0, 32'd5, 32'd0, "REM: 0 % 5 = 0");
        execute_division(`INST_REMU, 32'd0, 32'd5, 32'd0, "REMU: 0 % 5 = 0");
        
        // ========== LARGE NUMBER TESTS ==========
        $display("Testing large numbers...");
        execute_division(`INST_DIVU, 32'hFFFFFFFF, 32'hFFFFFFFF, 32'd1, "DIVU: MAX / MAX = 1");
        execute_division(`INST_REMU, 32'hFFFFFFFF, 32'hFFFFFFFF, 32'd0, "REMU: MAX % MAX = 0");
        execute_division(`INST_DIV, 32'h7FFFFFFF, 32'd2, 32'h3FFFFFFF, "DIV: MAX_SIGNED / 2");
        
        // ========== POWER OF 2 TESTS ==========
        $display("Testing power of 2 divisions...");
        execute_division(`INST_DIVU, 32'h80000000, 32'h40000000, 32'd2, "DIVU: 2^31 / 2^30 = 2");
        execute_division(`INST_DIVU, 32'h10000000, 32'h1000, 32'h10000, "DIVU: 2^28 / 2^12 = 2^16");
        
        // ========== TEST SUMMARY ==========
        repeat(5) @(posedge clk_i);
        
        $display("========================================");
        $display("Test Summary:");
        $display("Total Tests: %0d", test_count);
        $display("Passed:      %0d", pass_count);
        $display("Failed:      %0d", fail_count);
        $display("Success Rate: %.1f%%", (pass_count * 100.0) / test_count);
        $display("========================================");
        
        if (fail_count == 0) begin
            $display("🎉 ALL TESTS PASSED! 🎉");
        end else begin
            $display("❌ %0d TEST(S) FAILED", fail_count);
        end
        
        $finish;
    end

    // ========== TIMEOUT WATCHDOG ==========
    initial begin
        #1000000; // 1ms timeout
        $display("ERROR: Testbench timeout!");
        $finish;
    end

    // ========== WAVEFORM DUMP ==========
    initial begin
        $dumpfile("riscv_base_divider_tb.vcd");
        $dumpvars(0, riscv_base_divider_tb);
    end

endmodule

riscv_base_divider_tb.vcd
$date
	Tue Sep 09 14:55:46 2025
$end
$version
	Icarus Verilog
$end
$timescale
	1ps
$end
$scope module riscv_base_divider_tb $end
$var wire 32 ! writeback_value_o [31:0] $end
$var wire 1 " writeback_valid_o $end
$var reg 1 # clk_i $end
$var reg 32 $ expected_result [31:0] $end
$var reg 1 % opcode_invalid_i $end
$var reg 32 & opcode_opcode_i [31:0] $end
$var reg 32 ' opcode_pc_i [31:0] $end
$var reg 5 ( opcode_ra_idx_i [4:0] $end
$var reg 32 ) opcode_ra_operand_i [31:0] $end
$var reg 5 * opcode_rb_idx_i [4:0] $end
$var reg 32 + opcode_rb_operand_i [31:0] $end
$var reg 5 , opcode_rd_idx_i [4:0] $end
$var reg 1 - opcode_valid_i $end
$var reg 1 . rst_i $end
$var reg 1600 / test_name [1599:0] $end
$var integer 32 0 fail_count [31:0] $end
$var integer 32 1 pass_count [31:0] $end
$var integer 32 2 test_count [31:0] $end
$scope module dut $end
$var wire 1 # clk_i $end
$var wire 1 3 div_complete_w $end
$var wire 1 4 div_operation_w $end
$var wire 1 5 div_rem_inst_w $end
$var wire 1 6 div_start_w $end
$var wire 1 7 dividend_negative_w $end
$var wire 1 8 divisor_negative_w $end
$var wire 1 % opcode_invalid_i $end
$var wire 32 9 opcode_opcode_i [31:0] $end
$var wire 32 : opcode_pc_i [31:0] $end
$var wire 5 ; opcode_ra_idx_i [4:0] $end
$var wire 32 < opcode_ra_operand_i [31:0] $end
$var wire 5 = opcode_rb_idx_i [4:0] $end
$var wire 32 > opcode_rb_operand_i [31:0] $end
$var wire 5 ? opcode_rd_idx_i [4:0] $end
$var wire 1 - opcode_valid_i $end
$var wire 1 @ overflow_w $end
$var wire 1 A result_negative_w $end
$var wire 1 . rst_i $end
$var wire 1 B signed_operation_w $end
$var wire 1 C special_case_w $end
$var wire 1 D valid_div_req_w $end
$var wire 1 " writeback_valid_o $end
$var wire 32 E writeback_value_o [31:0] $end
$var wire 1 F inst_remu_w $end
$var wire 1 G inst_rem_w $end
$var wire 1 H inst_divu_w $end
$var wire 1 I inst_div_w $end
$var wire 32 J final_remainder_w [31:0] $end
$var wire 32 K final_quotient_w [31:0] $end
$var wire 32 L divisor_abs_w [31:0] $end
$var wire 32 M dividend_abs_w [31:0] $end
$var wire 1 N div_by_zero_w $end
$var reg 6 O cycle_counter_q [5:0] $end
$var reg 1 P div_busy_q $end
$var reg 1 Q div_inst_q $end
$var reg 32 R divisor_q [31:0] $end
$var reg 1 S invert_result_q $end
$var reg 32 T quotient_q [31:0] $end
$var reg 32 U remainder_q [31:0] $end
$var reg 32 V result_q [31:0] $end
$var reg 1 W valid_q $end
$upscope $end
$scope task check_result $end
$upscope $end
$scope task execute_division $end
$var reg 32 X dividend [31:0] $end
$var reg 32 Y divisor [31:0] $end
$var reg 32 Z expected [31:0] $end
$var reg 1600 [ name [1599:0] $end
$var reg 32 \ opcode [31:0] $end
$upscope $end
$scope task reset_system $end
$upscope $end
$upscope $end
$enddefinitions $end
$comment Show the parameter values. $end
$dumpall
$end
#0
$dumpvars
bx \
bx [
bx Z
bx Y
bx X
0W
b0 V
b0 U
b0 T
0S
b0 R
0Q
0P
b0 O
1N
b0 M
b0 L
b0 K
b0 J
0I
0H
0G
0F
b0 E
0D
0C
0B
0A
0@
b0 ?
b0 >
b0 =
b0 <
b0 ;
b0 :
b0 9
08
07
06
05
04
03
b0 2
b0 1
b0 0
bx /
1.
0-
b0 ,
b0 +
b0 *
b0 )
b0 (
b0 '
b0 &
0%
bx $
0#
0"
b0 !
$end
#5000
1#
#10000
0#
#15000
1#
#20000
0#
#25000
0.
1#
#30000
0#
#35000
1#
#40000
0#
#45000
16
1D
15
14
1B
b11 L
b10100 M
1I
0N
b11 +
b11 >
b10100 )
b10100 <
b11 *
b11 =
b10 (
b10 ;
b1 ,
b1 ?
b1000000000000 '
b1000000000000 :
b10000000000100000000110011 &
b10000000000100000000110011 9
1-
b110 $
b10001000100100101010110001110100010000000110010001100000010000000101111001000000011001100100000001111010010000000110110 /
b10001000100100101010110001110100010000000110010001100000010000000101111001000000011001100100000001111010010000000110110 [
b110 Z
b11 Y
b10100 X
b10000000000100000000110011 \
1#
#50000
0#
#55000
b10100 K
1P
b100000 O
1Q
b11 R
b10100 T
06
0D
0-
1#
#60000
0#
#65000
b101000 K
b101000 T
b11111 O
1#
#70000
0#
#75000
b1010000 K
b11110 O
b1010000 T
1#
#80000
0#
#85000
b10100000 K
b10100000 T
b11101 O
1#
#90000
0#
#95000
b101000000 K
b11100 O
b101000000 T
1#
#100000
0#
#105000
b1010000000 K
b1010000000 T
b11011 O
1#
#110000
0#
#115000
b10100000000 K
b11010 O
b10100000000 T
1#
#120000
0#
#125000
b101000000000 K
b101000000000 T
b11001 O
1#
#130000
0#
#135000
b1010000000000 K
b11000 O
b1010000000000 T
1#
#140000
0#
#145000
b10100000000000 K
b10100000000000 T
b10111 O
1#
#150000
0#
#155000
b101000000000000 K
b10110 O
b101000000000000 T
1#
#160000
0#
#165000
b1010000000000000 K
b1010000000000000 T
b10101 O
1#
#170000
0#
#175000
b10100000000000000 K
b10100 O
b10100000000000000 T
1#
#180000
0#
#185000
b101000000000000000 K
b101000000000000000 T
b10011 O
1#
#190000
0#
#195000
b1010000000000000000 K
b10010 O
b1010000000000000000 T
1#
#200000
0#
#205000
b10100000000000000000 K
b10100000000000000000 T
b10001 O
1#
#210000
0#
#215000
b101000000000000000000 K
b10000 O
b101000000000000000000 T
1#
#220000
0#
#225000
b1010000000000000000000 K
b1010000000000000000000 T
b1111 O
1#
#230000
0#
#235000
b10100000000000000000000 K
b1110 O
b10100000000000000000000 T
1#
#240000
0#
#245000
b101000000000000000000000 K
b101000000000000000000000 T
b1101 O
1#
#250000
0#
#255000
b1010000000000000000000000 K
b1100 O
b1010000000000000000000000 T
1#
#260000
0#
#265000
b10100000000000000000000000 K
b10100000000000000000000000 T
b1011 O
1#
#270000
0#
#275000
b101000000000000000000000000 K
b1010 O
b101000000000000000000000000 T
1#
#280000
0#
#285000
b1010000000000000000000000000 K
b1010000000000000000000000000 T
b1001 O
1#
#290000
0#
#295000
b10100000000000000000000000000 K
b1000 O
b10100000000000000000000000000 T
1#
#300000
0#
#305000
b101000000000000000000000000000 K
b101000000000000000000000000000 T
b111 O
1#
#310000
0#
#315000
b1010000000000000000000000000000 K
b110 O
b1010000000000000000000000000000 T
1#
#320000
0#
#325000
b10100000000000000000000000000000 K
b10100000000000000000000000000000 T
b101 O
1#
#330000
0#
#335000
b1000000000000000000000000000000 K
b1 J
b100 O
b1000000000000000000000000000000 T
b1 U
1#
#340000
0#
#345000
b10000000000000000000000000000000 K
b10 J
b10000000000000000000000000000000 T
b10 U
b11 O
1#
#350000
0#
#355000
b1 K
b10 O
b1 T
b10 U
1#
#360000
0#
#365000
b11 K
b1 J
b11 T
b1 U
b1 O
1#
#370000
0#
#375000
13
b110 K
b10 J
b0 O
b110 T
b10 U
1#
#380000
0#
#385000
03
b110 !
b110 E
b110 V
1"
1W
0P
1#
#390000
0#
#395000
0"
0W
b1 1
b1 2
1#
#400000
0#
#405000
1#
#410000
0#
#415000
16
1D
b1010 L
b1100100 M
b1010 +
b1010 >
b1100100 )
b1100100 <
1-
b1010 $
b10001000100100101010110001110100010000000110001001100000011000000100000001011110010000000110001001100000010000000111101001000000011000100110000 /
b10001000100100101010110001110100010000000110001001100000011000000100000001011110010000000110001001100000010000000111101001000000011000100110000 [
b1010 Z
b1010 Y
b1100100 X
1#
#420000
0#
#425000
b1100100 K
b0 J
b1100100 T
b0 U
b1010 R
b100000 O
1P
06
0D
0-
1#
#430000
0#
#435000
b11001000 K
b11111 O
b11001000 T
1#
#440000
0#
#445000
b110010000 K
b110010000 T
b11110 O
1#
#450000
0#
#455000
b1100100000 K
b11101 O
b1100100000 T
1#
#460000
0#
#465000
b11001000000 K
b11001000000 T
b11100 O
1#
#470000
0#
#475000
b110010000000 K
b11011 O
b110010000000 T
1#
#480000
0#
#485000
b1100100000000 K
b1100100000000 T
b11010 O
1#
#490000
0#
#495000
b11001000000000 K
b11001 O
b11001000000000 T
1#
#500000
0#
#505000
b110010000000000 K
b110010000000000 T
b11000 O
1#
#510000
0#
#515000
b1100100000000000 K
b10111 O
b1100100000000000 T
1#
#520000
0#
#525000
b11001000000000000 K
b11001000000000000 T
b10110 O
1#
#530000
0#
#535000
b110010000000000000 K
b10101 O
b110010000000000000 T
1#
#540000
0#
#545000
b1100100000000000000 K
b1100100000000000000 T
b10100 O
1#
#550000
0#
#555000
b11001000000000000000 K
b10011 O
b11001000000000000000 T
1#
#560000
0#
#565000
b110010000000000000000 K
b110010000000000000000 T
b10010 O
1#
#570000
0#
#575000
b1100100000000000000000 K
b10001 O
b1100100000000000000000 T
1#
#580000
0#
#585000
b11001000000000000000000 K
b11001000000000000000000 T
b10000 O
1#
#590000
0#
#595000
b110010000000000000000000 K
b1111 O
b110010000000000000000000 T
1#
#600000
0#
#605000
b1100100000000000000000000 K
b1100100000000000000000000 T
b1110 O
1#
#610000
0#
#615000
b11001000000000000000000000 K
b1101 O
b11001000000000000000000000 T
1#
#620000
0#
#625000
b110010000000000000000000000 K
b110010000000000000000000000 T
b1100 O
1#
#630000
0#
#635000
b1100100000000000000000000000 K
b1011 O
b1100100000000000000000000000 T
1#
#640000
0#
#645000
b11001000000000000000000000000 K
b11001000000000000000000000000 T
b1010 O
1#
#650000
0#
#655000
b110010000000000000000000000000 K
b1001 O
b110010000000000000000000000000 T
1#
#660000
0#
#665000
b1100100000000000000000000000000 K
b1100100000000000000000000000000 T
b1000 O
1#
#670000
0#
#675000
b11001000000000000000000000000000 K
b111 O
b11001000000000000000000000000000 T
1#
#680000
0#
#685000
b10010000000000000000000000000000 K
b1 J
b10010000000000000000000000000000 T
b1 U
b110 O
1#
#690000
0#
#695000
b100000000000000000000000000000 K
b11 J
b101 O
b100000000000000000000000000000 T
b11 U
1#
#700000
0#
#705000
b1000000000000000000000000000000 K
b110 J
b1000000000000000000000000000000 T
b110 U
b100 O
1#
#710000
0#
#715000
b10000000000000000000000000000001 K
b10 J
b11 O
b10000000000000000000000000000001 T
b10 U
1#
#720000
0#
#725000
b10 K
b101 J
b10 T
b101 U
b10 O
1#
#730000
0#
#735000
b101 K
b0 J
b1 O
b101 T
b0 U
1#
#740000
0#
#745000
b1010 K
13
b1010 T
b0 O
1#
#750000
0#
#755000
03
0P
1"
1W
b1010 !
b1010 E
b1010 V
1#
#760000
0#
#765000
0"
0W
b10 1
b10 2
1#
#770000
0#
#775000
1#
#780000
0#
#785000
16
1D
b1 L
b1 M
b1 +
b1 >
b1 )
b1 <
1-
b1 $
b100010001001001010101100011101000100000001100010010000000101111001000000011000100100000001111010010000000110001 /
b100010001001001010101100011101000100000001100010010000000101111001000000011000100100000001111010010000000110001 [
b1 Z
b1 Y
b1 X
1#
#790000
0#
#795000
b1 K
1P
b100000 O
b1 R
b1 T
06
0D
0-
1#
#800000
0#
#805000
b10 K
b10 T
b11111 O
1#
#810000
0#
#815000
b100 K
b11110 O
b100 T
1#
#820000
0#
#825000
b1000 K
b1000 T
b11101 O
1#
#830000
0#
#835000
b10000 K
b11100 O
b10000 T
1#
#840000
0#
#845000
b100000 K
b100000 T
b11011 O
1#
#850000
0#
#855000
b1000000 K
b11010 O
b1000000 T
1#
#860000
0#
#865000
b10000000 K
b10000000 T
b11001 O
1#
#870000
0#
#875000
b100000000 K
b11000 O
b100000000 T
1#
#880000
0#
#885000
b1000000000 K
b1000000000 T
b10111 O
1#
#890000
0#
#895000
b10000000000 K
b10110 O
b10000000000 T
1#
#900000
0#
#905000
b100000000000 K
b100000000000 T
b10101 O
1#
#910000
0#
#915000
b1000000000000 K
b10100 O
b1000000000000 T
1#
#920000
0#
#925000
b10000000000000 K
b10000000000000 T
b10011 O
1#
#930000
0#
#935000
b100000000000000 K
b10010 O
b100000000000000 T
1#
#940000
0#
#945000
b1000000000000000 K
b1000000000000000 T
b10001 O
1#
#950000
0#
#955000
b10000000000000000 K
b10000 O
b10000000000000000 T
1#
#960000
0#
#965000
b100000000000000000 K
b100000000000000000 T
b1111 O
1#
#970000
0#
#975000
b1000000000000000000 K
b1110 O
b1000000000000000000 T
1#
#980000
0#
#985000
b10000000000000000000 K
b10000000000000000000 T
b1101 O
1#
#990000
0#
#995000
b100000000000000000000 K
b1100 O
b100000000000000000000 T
1#
#1000000
0#
#1005000
b1000000000000000000000 K
b1000000000000000000000 T
b1011 O
1#
#1010000
0#
#1015000
b10000000000000000000000 K
b1010 O
b10000000000000000000000 T
1#
#1020000
0#
