riscv_base_defines.v
// Định nghĩa macro trong ALU
`define ALU_NONE                        4'b0000
`define ALU_SHIFT_LEFT                  4'b0001
`define ALU_SHIFT_RIGHT                 4'b0010
`define ALU_SHIFT_RIGHT_ARITHMETIC      4'b0011
`define ALU_ADD                         4'b0100
`define ALU_SUB                         4'b0101
`define ALU_AND                         4'b0110
`define ALU_OR                          4'b0111
`define ALU_XOR                         4'b1000
`define ALU_LESS_THAN                   4'b1001
`define ALU_LESS_THAN_UNSIGNED          4'b1010

// Định nghĩa macro trong bộ NHÂN
//1. mul
// mul
`define INST_MUL 32'h2000033
`define INST_MUL_MASK 32'hfe00707f

//2. mulh
`define INST_MULH 32'h2001033
`define INST_MULH_MASK 32'hfe00707f

//3. mulhsu
`define INST_MULHSU 32'h2002033
`define INST_MULHSU_MASK 32'hfe00707f

//4. mulhu
`define INST_MULHU 32'h2003033
`define INST_MULHU_MASK 32'hfe00707f

// Định nghĩa macro trong bộ CHIA
//1. div
`define INST_DIV 32'h2004033
`define INST_DIV_MASK 32'hfe00707f

//2. divu
`define INST_DIVU 32'h2005033
`define INST_DIVU_MASK 32'hfe00707f

//3. rem
`define INST_REM 32'h2006033
`define INST_REM_MASK 32'hfe00707f

//4. remu
`define INST_REMU 32'h2007033
`define INST_REMU_MASK 32'hfe00707f

main/riscv_base_multiplier.v
module riscv_base_multiplier (
    // Inputs
    input           clk_i,
    input           rst_i,
    input           opcode_valid_i,
    input  [31:0]   opcode_opcode_i,
    input  [31:0]   opcode_pc_i,
    input           opcode_invalid_i,
    input  [4:0]    opcode_rd_idx_i,
    input  [4:0]    opcode_ra_idx_i,
    input  [4:0]    opcode_rb_idx_i,
    input  [31:0]   opcode_ra_operand_i, // Toán hạng a
    input  [31:0]   opcode_rb_operand_i, // Toán hạng b
    input           hold_i,
    // Outputs
    output [31:0]   writeback_value_o
);

    // Bao gồm định nghĩa RISC-V
    `include "riscv_base_defines.v"

    // Tham số pipeline
    localparam MULT_STAGES = 2; // 2 giai đoạn

    //-------------------------------------------------------------
    // Thanh ghi và dây
    //-------------------------------------------------------------
    reg  [31:0] result_e2_q;    // Thanh ghi giai đoạn E2
    reg         valid_e1_q;     // Thanh ghi valid giai đoạn E1
    reg         mulhi_sel_e1_q; // Chọn phần cao/thấp
    wire [63:0] mult_result_w;  // Kết quả nhân 64-bit
    wire [31:0] result_w;       // Kết quả tổ hợp

    //-------------------------------------------------------------
    // Giải mã lệnh
    //-------------------------------------------------------------
    wire inst_mul_w    = (opcode_opcode_i & `INST_MUL_MASK)    == `INST_MUL;
    wire inst_mulh_w   = (opcode_opcode_i & `INST_MULH_MASK)   == `INST_MULH;
    wire inst_mulhsu_w = (opcode_opcode_i & `INST_MULHSU_MASK) == `INST_MULHSU;
    wire inst_mulhu_w  = (opcode_opcode_i & `INST_MULHU_MASK)  == `INST_MULHU;
    wire mult_inst_w   = inst_mul_w | inst_mulh_w | inst_mulhsu_w | inst_mulhu_w;

    //-------------------------------------------------------------
    // Lựa chọn toán hạng (sign/zero extension)
    //-------------------------------------------------------------
    wire [63:0] operand_a_w = (inst_mulh_w | inst_mulhsu_w) ? 
                             {{32{opcode_ra_operand_i[31]}}, opcode_ra_operand_i} : // Có dấu
                             {32'h0, opcode_ra_operand_i};                         // Không dấu
    wire [63:0] operand_b_w = inst_mulh_w ? 
                             {{32{opcode_rb_operand_i[31]}}, opcode_rb_operand_i} : // Có dấu
                             {32'h0, opcode_rb_operand_i};                         // Không dấu
    wire mulhi_sel_w = inst_mulh_w | inst_mulhsu_w | inst_mulhu_w;

    //-------------------------------------------------------------
    // Giai đoạn E1: Lưu toán hạng và valid
    //-------------------------------------------------------------
    reg [63:0] operand_a_e1_q;
    reg [63:0] operand_b_e1_q;

    always @(posedge clk_i or posedge rst_i) begin
        if (rst_i) begin
            operand_a_e1_q <= 64'b0;
            operand_b_e1_q <= 64'b0;
            valid_e1_q <= 1'b0;
            mulhi_sel_e1_q <= 1'b0;
        end else if (hold_i) begin
            operand_a_e1_q <= operand_a_e1_q;
            operand_b_e1_q <= operand_b_e1_q;
            valid_e1_q <= valid_e1_q;
            mulhi_sel_e1_q <= mulhi_sel_e1_q;
        end else begin
            operand_a_e1_q <= operand_a_w;
            operand_b_e1_q <= operand_b_w;
            valid_e1_q <= opcode_valid_i && mult_inst_w;
            mulhi_sel_e1_q <= mulhi_sel_w;
        end
    end

    //-------------------------------------------------------------
    // Bộ nhân low-level (sử dụng toán tử *)
    //-------------------------------------------------------------
    assign mult_result_w = $signed(operand_a_e1_q) * $signed(operand_b_e1_q);

    // Lựa chọn phần cao hoặc thấp
    assign result_w = mulhi_sel_e1_q ? mult_result_w[63:32] : mult_result_w[31:0];

    //-------------------------------------------------------------
    // Giai đoạn E2: Lưu kết quả
    //-------------------------------------------------------------
    always @(posedge clk_i or posedge rst_i) begin
        if (rst_i)
            result_e2_q <= 32'b0;
        else if (~hold_i && valid_e1_q)
            result_e2_q <= result_w;
        else if (~hold_i)
            result_e2_q <= 32'b0; // Xóa kết quả nếu không valid
    end

    //-------------------------------------------------------------
    // Đầu ra
    //-------------------------------------------------------------
    assign writeback_value_o = opcode_invalid_i ? 32'b0 : result_e2_q;

endmodule

riscv_base_multiplier_tb.v
`timescale 1ns/1ps
`include "riscv_base_defines.v"
`include "riscv_base_multiplier.v"

module riscv_base_multiplier_tb;
    reg         clk_i;
    reg         rst_i;
    reg         opcode_valid_i;
    reg  [31:0] opcode_opcode_i;
    reg  [31:0] opcode_pc_i;
    reg         opcode_invalid_i;
    reg  [4:0]  opcode_rd_idx_i;
    reg  [4:0]  opcode_ra_idx_i;
    reg  [4:0]  opcode_rb_idx_i;
    reg  [31:0] opcode_ra_operand_i;
    reg  [31:0] opcode_rb_operand_i;
    reg         hold_i;
    wire [31:0] writeback_value_o;

    // Khởi tạo module
    riscv_base_multiplier uut (
        .clk_i(clk_i),
        .rst_i(rst_i),
        .opcode_valid_i(opcode_valid_i),
        .opcode_opcode_i(opcode_opcode_i),
        .opcode_pc_i(opcode_pc_i),
        .opcode_invalid_i(opcode_invalid_i),
        .opcode_rd_idx_i(opcode_rd_idx_i),
        .opcode_ra_idx_i(opcode_ra_idx_i),
        .opcode_rb_idx_i(opcode_rb_idx_i),
        .opcode_ra_operand_i(opcode_ra_operand_i),
        .opcode_rb_operand_i(opcode_rb_operand_i),
        .hold_i(hold_i),
        .writeback_value_o(writeback_value_o)
    );

    // Tạo xung nhịp
    initial begin
        clk_i = 0;
        forever #5 clk_i = ~clk_i; // Chu kỳ 10ns
    end

    // Tạo file VCD để debug
    initial begin
        $dumpfile("riscv_base_multiplier_tb.vcd");
        $dumpvars(0, riscv_base_multiplier_tb);
    end

    // Kịch bản kiểm tra
    initial begin
        // Khởi tạo các tín hiệu
        rst_i = 1;
        opcode_valid_i = 0;
        opcode_invalid_i = 0;
        hold_i = 0;
        opcode_opcode_i = 32'h0;
        opcode_pc_i = 32'h0;        // Khởi tạo tín hiệu không dùng
        opcode_rd_idx_i = 5'h0;
        opcode_ra_idx_i = 5'h0;
        opcode_rb_idx_i = 5'h0;
        opcode_ra_operand_i = 32'h0;
        opcode_rb_operand_i = 32'h0;
        #30; // Đợi 3 chu kỳ để đảm bảo reset ổn định
        rst_i = 0;
        #30; // Đợi thêm trước khi bắt đầu test

        // Test case 1: MUL - Số dương nhỏ (5 * 3)
        $display("\nTest case 1: MUL 5 * 3");
        opcode_valid_i = 1;
        opcode_opcode_i = `INST_MUL; // 02000033
        opcode_ra_operand_i = 32'h5;
        opcode_rb_operand_i = 32'h3;
        #30; // Đợi 3 chu kỳ để xử lý độ trễ
        if (writeback_value_o !== 32'hF)
            $display("Error: MUL 5 * 3 = %h (expect 0xF)", writeback_value_o);
        else
            $display("Pass: MUL 5 * 3 = %h", writeback_value_o);

        // Test case 2: MUL - Số âm * Số dương (-5 * 3)
        $display("\nTest case 2: MUL -5 * 3");
        opcode_ra_operand_i = -32'h5; // 0xFFFFFFFB
        opcode_rb_operand_i = 32'h3;
        #30;
        if (writeback_value_o !== -32'hF) // 0xFFFFFFF1
            $display("Error: MUL -5 * 3 = %h (expect 0xFFFFFFF1)", writeback_value_o);
        else
            $display("Pass: MUL -5 * 3 = %h", writeback_value_o);

        // Test case 3: MULH - Số âm * Số dương (-5 * 3)
        $display("\nTest case 3: MULH -5 * 3");
        opcode_opcode_i = `INST_MULH; // 02002033
        opcode_ra_operand_i = -32'h5;
        opcode_rb_operand_i = 32'h3;
        #30;
        if (writeback_value_o !== -32'h1) // 0xFFFFFFFF
            $display("Error: MULH -5 * 3 = %h (expect 0xFFFFFFFF)", writeback_value_o);
        else
            $display("Pass: MULH -5 * 3 = %h", writeback_value_o);

        // Test case 4: MULHSU - Số âm * Số dương không dấu (-5 * 3)
        $display("\nTest case 4: MULHSU -5 * 3");
        opcode_opcode_i = `INST_MULHSU; // 02003033
        opcode_ra_operand_i = -32'h5;
        opcode_rb_operand_i = 32'h3;
        #30;
        if (writeback_value_o !== 32'hFFFFFFFF)
            $display("Error: MULHSU -5 * 3 = %h (expect 0xFFFFFFFF)", writeback_value_o);
        else
            $display("Pass: MULHSU -5 * 3 = %h", writeback_value_o);

        // Test case 5: MULHU - Số không dấu lớn (0xFFFFFFFF * 2)
        $display("\nTest case 5: MULHU 0xFFFFFFFF * 2");
        opcode_opcode_i = `INST_MULHU; // 02003033
        opcode_ra_operand_i = 32'hFFFFFFFF;
        opcode_rb_operand_i = 32'h2;
        #30;
        if (writeback_value_o !== 32'h1)
            $display("Error: MULHU 0xFFFFFFFF * 2 = %h (expect 0x1)", writeback_value_o);
        else
            $display("Pass: MULHU 0xFFFFFFFF * 2 = %h", writeback_value_o);

        // Test case 6: MUL - Hai số âm (-5 * -3)
        $display("\nTest case 6: MUL -5 * -3");
        opcode_opcode_i = `INST_MUL;
        opcode_ra_operand_i = -32'h5; // 0xFFFFFFFB
        opcode_rb_operand_i = -32'h3; // 0xFFFFFFFD
        #30;
        if (writeback_value_o !== 32'hF) // 15
            $display("Error: MUL -5 * -3 = %h (expect 0xF)", writeback_value_o);
        else
            $display("Pass: MUL -5 * -3 = %h", writeback_value_o);

        // Test case 7: MUL - Nhân với 0 (0 * 5)
        $display("\nTest case 7: MUL 0 * 5");
        opcode_opcode_i = `INST_MUL;
        opcode_ra_operand_i = 32'h0;
        opcode_rb_operand_i = 32'h5;
        #30;
        if (writeback_value_o !== 32'h0)
            $display("Error: MUL 0 * 5 = %h (expect 0x0)", writeback_value_o);
        else
            $display("Pass: MUL 0 * 5 = %h", writeback_value_o);

        // Test case 8: MUL - Giá trị âm nhỏ nhất (0x80000000 * 1)
        $display("\nTest case 8: MUL 0x80000000 * 1");
        opcode_opcode_i = `INST_MUL;
        opcode_ra_operand_i = 32'h80000000; // -2^31
        opcode_rb_operand_i = 32'h1;
        #30;
        if (writeback_value_o !== 32'h80000000)
            $display("Error: MUL 0x80000000 * 1 = %h (expect 0x80000000)", writeback_value_o);
        else
            $display("Pass: MUL 0x80000000 * 1 = %h", writeback_value_o);

        // Test case 9: Kiểm tra tín hiệu hold
        $display("\nTest case 9: Testing hold signal");
        opcode_opcode_i = `INST_MUL;
        opcode_ra_operand_i = 32'h5;
        opcode_rb_operand_i = 32'h3;
        hold_i = 1;
        #30;
        if (writeback_value_o !== 32'h0) // Giả sử hold giữ output ở 0
            $display("Error: Hold active, expected 0x0, got %h", writeback_value_o);
        else
            $display("Pass: Hold active, output = %h", writeback_value_o);
        hold_i = 0;
        #30;
        if (writeback_value_o !== 32'hF)
            $display("Error: Hold released, MUL 5 * 3 = %h (expect 0xF)", writeback_value_o);
        else
            $display("Pass: Hold released, MUL 5 * 3 = %h", writeback_value_o);

        // Test case 10: Kiểm tra opcode không hợp lệ
        $display("\nTest case 10: Testing invalid opcode");
        opcode_invalid_i = 1;
        opcode_valid_i = 0; // Đảm bảo valid=0 khi invalid=1
        #30;
        if (writeback_value_o !== 32'h0)
            $display("Error: Invalid opcode, expected 0x0, got %h", writeback_value_o);
        else
            $display("Pass: Invalid opcode, output = %h", writeback_value_o);

        // Kết thúc test
        #20;
        $display("\nAll tests completed!");
        $finish;
    end

    // Monitor kết quả
    initial begin
        $monitor("Time=%0d rst=%b valid=%b op=%h a=%h b=%h result=%h",
            $time, rst_i, opcode_valid_i, opcode_opcode_i,
            opcode_ra_operand_i, opcode_rb_operand_i, writeback_value_o);
    end
endmodule

riscv_base_multiplier_tb.vcd
$date
	Fri Sep 12 11:09:56 2025
$end
$version
	Icarus Verilog
$end
$timescale
	1ps
$end
$scope module riscv_base_multiplier_tb $end
$var wire 32 ! writeback_value_o [31:0] $end
$var reg 1 " clk_i $end
$var reg 1 # hold_i $end
$var reg 1 $ opcode_invalid_i $end
$var reg 32 % opcode_opcode_i [31:0] $end
$var reg 32 & opcode_pc_i [31:0] $end
$var reg 5 ' opcode_ra_idx_i [4:0] $end
$var reg 32 ( opcode_ra_operand_i [31:0] $end
$var reg 5 ) opcode_rb_idx_i [4:0] $end
$var reg 32 * opcode_rb_operand_i [31:0] $end
$var reg 5 + opcode_rd_idx_i [4:0] $end
$var reg 1 , opcode_valid_i $end
$var reg 1 - rst_i $end
$scope module uut $end
$var wire 1 " clk_i $end
$var wire 1 # hold_i $end
$var wire 1 . mulhi_sel_w $end
$var wire 1 / mult_inst_w $end
$var wire 1 $ opcode_invalid_i $end
$var wire 32 0 opcode_opcode_i [31:0] $end
$var wire 32 1 opcode_pc_i [31:0] $end
$var wire 5 2 opcode_ra_idx_i [4:0] $end
$var wire 32 3 opcode_ra_operand_i [31:0] $end
$var wire 5 4 opcode_rb_idx_i [4:0] $end
$var wire 32 5 opcode_rb_operand_i [31:0] $end
$var wire 5 6 opcode_rd_idx_i [4:0] $end
$var wire 1 , opcode_valid_i $end
$var wire 1 - rst_i $end
$var wire 32 7 writeback_value_o [31:0] $end
$var wire 32 8 result_w [31:0] $end
$var wire 64 9 operand_b_w [63:0] $end
$var wire 64 : operand_a_w [63:0] $end
$var wire 64 ; mult_result_w [63:0] $end
$var wire 1 < inst_mulhu_w $end
$var wire 1 = inst_mulhsu_w $end
$var wire 1 > inst_mulh_w $end
$var wire 1 ? inst_mul_w $end
$var parameter 32 @ MULT_STAGES $end
$var reg 1 A mulhi_sel_e1_q $end
$var reg 64 B operand_a_e1_q [63:0] $end
$var reg 64 C operand_b_e1_q [63:0] $end
$var reg 32 D result_e2_q [31:0] $end
$var reg 1 E valid_e1_q $end
$upscope $end
$upscope $end
$enddefinitions $end
$comment Show the parameter values. $end
$dumpall
b10 @
$end
#0
$dumpvars
0E
b0 D
b0 C
b0 B
0A
0?
0>
0=
0<
b0 ;
b0 :
b0 9
b0 8
b0 7
b0 6
b0 5
b0 4
b0 3
b0 2
b0 1
b0 0
0/
0.
1-
0,
b0 +
b0 *
b0 )
b0 (
b0 '
b0 &
b0 %
0$
0#
0"
b0 !
$end
#5000
1"
#10000
0"
#15000
1"
#20000
0"
#25000
1"
#30000
0"
0-
#35000
1"
#40000
0"
#45000
1"
#50000
0"
#55000
1"
#60000
1/
b11 9
b101 :
1?
0"
b11 *
b11 5
b101 (
b101 3
b10000000000000000000110011 %
b10000000000000000000110011 0
1,
#65000
b1111 8
1E
b1111 ;
b11 C
b101 B
1"
#70000
0"
#75000
b1111 !
b1111 7
b1111 D
1"
#80000
0"
#85000
1"
#90000
b11111111111111111111111111111011 :
0"
b11111111111111111111111111111011 (
b11111111111111111111111111111011 3
#95000
b11111111111111111111111111110001 8
b1011111111111111111111111111110001 ;
b11111111111111111111111111111011 B
1"
#100000
0"
#105000
b11111111111111111111111111110001 !
b11111111111111111111111111110001 7
b11111111111111111111111111110001 D
1"
#110000
0"
#115000
1"
#120000
1.
b1111111111111111111111111111111111111111111111111111111111111011 :
0?
1>
0"
b10000000000010000000110011 %
b10000000000010000000110011 0
#125000
b11111111111111111111111111111111 8
1A
b1111111111111111111111111111111111111111111111111111111111110001 ;
b1111111111111111111111111111111111111111111111111111111111111011 B
1"
#130000
0"
#135000
b11111111111111111111111111111111 !
b11111111111111111111111111111111 7
b11111111111111111111111111111111 D
1"
#140000
0"
#145000
1"
#150000
0>
1=
0"
b10000000000011000000110011 %
b10000000000011000000110011 0
#155000
1"
#160000
0"
#165000
1"
#170000
0"
#175000
1"
#180000
b10 9
b11111111111111111111111111111111 :
0=
1<
0"
b10 *
b10 5
b11111111111111111111111111111111 (
b11111111111111111111111111111111 3
b10000000000001000000110011 %
b10000000000001000000110011 0
#185000
b1 8
b10 C
b111111111111111111111111111111110 ;
b11111111111111111111111111111111 B
1"
#190000
0"
#195000
b1 !
b1 7
b1 D
1"
#200000
0"
#205000
1"
#210000
0.
1/
b11111111111111111111111111111101 9
b11111111111111111111111111111011 :
1?
0<
0"
b11111111111111111111111111111101 *
b11111111111111111111111111111101 5
b11111111111111111111111111111011 (
b11111111111111111111111111111011 3
b10000000000000000000110011 %
b10000000000000000000110011 0
#215000
b1111 8
0A
b11111111111111111111111111111101 C
b1111111111111111111111111111100000000000000000000000000000001111 ;
b11111111111111111111111111111011 B
1"
#220000
0"
#225000
b1111 !
b1111 7
b1111 D
1"
#230000
0"
#235000
1"
#240000
b101 9
b0 :
0"
b101 *
b101 5
b0 (
b0 3
#245000
b0 8
b101 C
b0 ;
b0 B
1"
#250000
0"
#255000
b0 !
b0 7
b0 D
1"
#260000
0"
#265000
1"
#270000
b1 9
b10000000000000000000000000000000 :
0"
b1 *
b1 5
b10000000000000000000000000000000 (
b10000000000000000000000000000000 3
#275000
b10000000000000000000000000000000 8
b1 C
b10000000000000000000000000000000 ;
b10000000000000000000000000000000 B
1"
#280000
0"
#285000
b10000000000000000000000000000000 !
b10000000000000000000000000000000 7
b10000000000000000000000000000000 D
1"
#290000
0"
#295000
1"
#300000
b11 9
b101 :
0"
1#
b11 *
b11 5
b101 (
b101 3
#305000
1"
#310000
0"
#315000
1"
#320000
0"
#325000
1"
#330000
0"
0#
#335000
b1111 8
b11 C
b1111 ;
b101 B
1"
#340000
0"
#345000
b1111 !
b1111 7
b1111 D
1"
#350000
0"
#355000
1"
#360000
b0 !
b0 7
0"
0,
1$
#365000
0E
1"
#370000
0"
#375000
b0 D
1"
