riscv_base_defines.v
// Định nghĩa macro trong ALU
`define ALU_NONE                        4'b0000
`define ALU_SHIFT_LEFT                  4'b0001
`define ALU_SHIFT_RIGHT                 4'b0010
`define ALU_SHIFT_RIGHT_ARITHMETIC      4'b0011
`define ALU_ADD                         4'b0100
`define ALU_SUB                         4'b0101
`define ALU_AND                         4'b0110
`define ALU_OR                          4'b0111
`define ALU_XOR                         4'b1000
`define ALU_LESS_THAN                   4'b1001
`define ALU_LESS_THAN_UNSIGNED          4'b1010

// Định nghĩa macro trong bộ NHÂN
//1. mul
// mul
`define INST_MUL 32'h2000033
`define INST_MUL_MASK 32'hfe00707f

//2. mulh
`define INST_MULH 32'h2001033
`define INST_MULH_MASK 32'hfe00707f

//3. mulhsu
`define INST_MULHSU 32'h2002033
`define INST_MULHSU_MASK 32'hfe00707f

//4. mulhu
`define INST_MULHU 32'h2003033
`define INST_MULHU_MASK 32'hfe00707f

// Định nghĩa macro trong bộ CHIA
//1. div
`define INST_DIV 32'h2004033
`define INST_DIV_MASK 32'hfe00707f

//2. divu
`define INST_DIVU 32'h2005033
`define INST_DIVU_MASK 32'hfe00707f

//3. rem
`define INST_REM 32'h2006033
`define INST_REM_MASK 32'hfe00707f

//4. remu
`define INST_REMU 32'h2007033
`define INST_REMU_MASK 32'hfe00707f

riscv_base_multiplier.v
module riscv_base_multiplier(
    input           clk_i,
    input           rst_i,
    input           hold_i,

    input           opcode_valid_i,
    input  [31:0]   opcode_opcode_i,
    input  [31:0]   opcode_pc_i,
    input           opcode_invalid_i,

    input  [4:0]    opcode_rd_idx_i,
    input  [4:0]    opcode_ra_idx_i,
    input  [4:0]    opcode_rb_idx_i,

    input  [31:0]   opcode_ra_operand_i,
    input  [31:0]   opcode_rb_operand_i,

    output [31:0]   writeback_value_o
);
    `include "riscv_base_defines.v"

    localparam MULT_STAGES = 2;

    // pipeline registers
    reg [32:0] operand_a_e1_q;
    reg [32:0] operand_b_e1_q;
    reg        mulhi_sel_e1_q;
    reg [31:0] result_e2_q;
    reg [31:0] result_e3_q;

    // temporary wires
    reg [32:0] operand_a_r;
    reg [32:0] operand_b_r;
    wire [63:0] mult_result_w;
    reg [31:0] result_r;

    // decode instruction
    wire inst_mul    = ((opcode_opcode_i & `INST_MUL_MASK)    == `INST_MUL);
    wire inst_mulh   = ((opcode_opcode_i & `INST_MULH_MASK)   == `INST_MULH);
    wire inst_mulhsu = ((opcode_opcode_i & `INST_MULHSU_MASK) == `INST_MULHSU);
    wire inst_mulhu  = ((opcode_opcode_i & `INST_MULHU_MASK)  == `INST_MULHU);

    wire mult_inst_w = inst_mul | inst_mulh | inst_mulhsu | inst_mulhu;

    // chọn operand A/B (có sign-extend hoặc zero-extend thành 33 bit)
    always @(*) begin
        if (inst_mulhsu) begin
            operand_a_r = {opcode_ra_operand_i[31], opcode_ra_operand_i};
            operand_b_r = {1'b0, opcode_rb_operand_i};
        end else if (inst_mulh) begin
            operand_a_r = {opcode_ra_operand_i[31], opcode_ra_operand_i};
            operand_b_r = {opcode_rb_operand_i[31], opcode_rb_operand_i};
        end else begin // MUL hoặc MULHU
            operand_a_r = {1'b0, opcode_ra_operand_i};
            operand_b_r = {1'b0, opcode_rb_operand_i};
        end
    end

    // pipeline stage E1
    always @(posedge clk_i or posedge rst_i) begin
        if (rst_i) begin
            operand_a_e1_q <= 33'b0;
            operand_b_e1_q <= 33'b0;
            mulhi_sel_e1_q <= 1'b0;
        end else if (hold_i) begin
            // giữ giá trị
            operand_a_e1_q <= operand_a_e1_q;
            operand_b_e1_q <= operand_b_e1_q;
            mulhi_sel_e1_q <= mulhi_sel_e1_q;
        end else if (opcode_valid_i && mult_inst_w) begin
            operand_a_e1_q <= operand_a_r;
            operand_b_e1_q <= operand_b_r;
            mulhi_sel_e1_q <= ~inst_mul; // chọn high phần khi không phải MUL
        end else begin
            operand_a_e1_q <= 33'b0;
            operand_b_e1_q <= 33'b0;
            mulhi_sel_e1_q <= 1'b0;
        end
    end

    // multiplier 33x33 -> 64 bit
    assign mult_result_w = $signed({{31{operand_a_e1_q[32]}}, operand_a_e1_q}) *
                           $signed({{31{operand_b_e1_q[32]}}, operand_b_e1_q});

    // chọn kết quả high/low
    always @(*) begin
        result_r = mulhi_sel_e1_q ? mult_result_w[63:32] : mult_result_w[31:0];
    end

    // pipeline stage E2
    always @(posedge clk_i or posedge rst_i) begin
        if (rst_i)
            result_e2_q <= 32'b0;
        else if (~hold_i)
            result_e2_q <= result_r;
    end

    // pipeline stage E3
    always @(posedge clk_i or posedge rst_i) begin
        if (rst_i)
            result_e3_q <= 32'b0;
        else if (~hold_i)
            result_e3_q <= result_e2_q;
    end

    // output chọn theo MULT_STAGES
    assign writeback_value_o = opcode_invalid_i ? 32'b0 :
                              (MULT_STAGES == 2) ? result_e2_q : result_e3_q;

endmodule

riscv_base_multiplier_tb.v
`timescale 1ns/1ps
`include "riscv_base_defines.v"
`include "riscv_base_multiplier.v"
module riscv_base_multiplier_tb();

    reg clk;
    reg rst;
    reg hold;

    reg          opcode_valid;
    reg [31:0]   opcode_opcode;
    reg [31:0]   opcode_pc;
    reg          opcode_invalid;

    reg [4:0]    opcode_rd_idx;
    reg [4:0]    opcode_ra_idx;
    reg [4:0]    opcode_rb_idx;

    reg [31:0]   opcode_ra_operand;
    reg [31:0]   opcode_rb_operand;

    wire [31:0]  writeback_value;

    // DUT
    riscv_base_multiplier dut (
        .clk_i(clk),
        .rst_i(rst),
        .hold_i(hold),
        .opcode_valid_i(opcode_valid),
        .opcode_opcode_i(opcode_opcode),
        .opcode_pc_i(opcode_pc),
        .opcode_invalid_i(opcode_invalid),
        .opcode_rd_idx_i(opcode_rd_idx),
        .opcode_ra_idx_i(opcode_ra_idx),
        .opcode_rb_idx_i(opcode_rb_idx),
        .opcode_ra_operand_i(opcode_ra_operand),
        .opcode_rb_operand_i(opcode_rb_operand),
        .writeback_value_o(writeback_value)
    );

    // clock
    always #5 clk = ~clk;

    // reference model
    function [31:0] ref_mul;
        input [31:0] a;
        input [31:0] b;
        input [31:0] opcode;

        reg [63:0] tmp;
    begin
        if ((opcode & `INST_MUL_MASK) == `INST_MUL) begin
            tmp = $signed(a) * $signed(b);
            ref_mul = tmp[31:0];
        end
        else if ((opcode & `INST_MULH_MASK) == `INST_MULH) begin
            tmp = $signed(a) * $signed(b);
            ref_mul = tmp[63:32];
        end
        else if ((opcode & `INST_MULHSU_MASK) == `INST_MULHSU) begin
            tmp = $signed(a) * b; // b treated as unsigned
            ref_mul = tmp[63:32];
        end
        else if ((opcode & `INST_MULHU_MASK) == `INST_MULHU) begin
            tmp = a * b; // both unsigned
            ref_mul = tmp[63:32];
        end
        else begin
            ref_mul = 32'h0;
        end
    end
    endfunction


    initial begin
        $dumpfile("riscv_base_multiplier_tb.vcd");
        $dumpvars(0, riscv_base_multiplier_tb);
    end

    // task test
    task run_case;
        input [31:0] op_a;
        input [31:0] op_b;
        input [31:0] opcode;
        reg [31:0] exp;
    begin
        @(negedge clk);
        opcode_ra_operand = op_a;
        opcode_rb_operand = op_b;
        opcode_opcode     = opcode;
        opcode_valid      = 1;
        opcode_invalid    = 0;
        hold              = 0;

        exp = ref_mul(op_a, op_b, opcode);

        // đợi pipeline 2 stage
        repeat(3) @(negedge clk);

        if (writeback_value !== exp) begin
            $display("FAIL: opcode=%h a=%0d b=%0d => got=%h expected=%h",
                     opcode, op_a, op_b, writeback_value, exp);
        end else begin
            $display("PASS: opcode=%h a=%0d b=%0d => result=%h",
                     opcode, op_a, op_b, writeback_value);
        end
    end
    endtask

    initial begin
        clk = 0; rst = 1; hold = 0;
        opcode_valid = 0; opcode_invalid = 0;
        opcode_opcode = 0;
        opcode_pc = 0;
        opcode_rd_idx = 0;
        opcode_ra_idx = 0;
        opcode_rb_idx = 0;
        opcode_ra_operand = 0;
        opcode_rb_operand = 0;

        #20 rst = 0;

        // Testcases
        run_case(32'd5, 32'd7, `INST_MUL);         // MUL
        run_case(-32'd8, 32'd3, `INST_MUL);        // MUL signed
        run_case(-32'd8, 32'd3, `INST_MULH);       // MULH
        run_case(-32'd8, 32'd3, `INST_MULHSU);     // MULHSU

        #1000;
        $finish;
    end

endmodule

riscv_base_multiplier_tb.vcd
$date
	Sat Sep 06 10:31:06 2025
$end
$version
	Icarus Verilog
$end
$timescale
	1ps
$end
$scope module riscv_base_multiplier_tb $end
$var wire 32 ! writeback_value [31:0] $end
$var reg 1 " clk $end
$var reg 1 # hold $end
$var reg 1 $ opcode_invalid $end
$var reg 32 % opcode_opcode [31:0] $end
$var reg 32 & opcode_pc [31:0] $end
$var reg 5 ' opcode_ra_idx [4:0] $end
$var reg 32 ( opcode_ra_operand [31:0] $end
$var reg 5 ) opcode_rb_idx [4:0] $end
$var reg 32 * opcode_rb_operand [31:0] $end
$var reg 5 + opcode_rd_idx [4:0] $end
$var reg 1 , opcode_valid $end
$var reg 1 - rst $end
$scope function ref_mul $end
$var reg 32 . a [31:0] $end
$var reg 32 / b [31:0] $end
$var reg 32 0 opcode [31:0] $end
$var reg 64 1 tmp [63:0] $end
$upscope $end
$scope module dut $end
$var wire 1 " clk_i $end
$var wire 1 # hold_i $end
$var wire 1 2 mult_inst_w $end
$var wire 1 $ opcode_invalid_i $end
$var wire 32 3 opcode_opcode_i [31:0] $end
$var wire 32 4 opcode_pc_i [31:0] $end
$var wire 5 5 opcode_ra_idx_i [4:0] $end
$var wire 32 6 opcode_ra_operand_i [31:0] $end
$var wire 5 7 opcode_rb_idx_i [4:0] $end
$var wire 32 8 opcode_rb_operand_i [31:0] $end
$var wire 5 9 opcode_rd_idx_i [4:0] $end
$var wire 1 , opcode_valid_i $end
$var wire 1 - rst_i $end
$var wire 32 : writeback_value_o [31:0] $end
$var wire 64 ; mult_result_w [63:0] $end
$var wire 1 < inst_mulhu $end
$var wire 1 = inst_mulhsu $end
$var wire 1 > inst_mulh $end
$var wire 1 ? inst_mul $end
$var parameter 32 @ MULT_STAGES $end
$var reg 1 A mulhi_sel_e1_q $end
$var reg 33 B operand_a_e1_q [32:0] $end
$var reg 33 C operand_a_r [32:0] $end
$var reg 33 D operand_b_e1_q [32:0] $end
$var reg 33 E operand_b_r [32:0] $end
$var reg 32 F result_e2_q [31:0] $end
$var reg 32 G result_e3_q [31:0] $end
$var reg 32 H result_r [31:0] $end
$upscope $end
$scope task run_case $end
$var reg 32 I exp [31:0] $end
$var reg 32 J op_a [31:0] $end
$var reg 32 K op_b [31:0] $end
$var reg 32 L opcode [31:0] $end
$upscope $end
$upscope $end
$enddefinitions $end
$comment Show the parameter values. $end
$dumpall
b10 @
$end
#0
$dumpvars
bx L
bx K
bx J
bx I
b0 H
b0 G
b0 F
b0 E
b0 D
b0 C
b0 B
0A
0?
0>
0=
0<
b0 ;
b0 :
b0 9
b0 8
b0 7
b0 6
b0 5
b0 4
b0 3
02
bx 1
bx 0
bx /
bx .
1-
0,
b0 +
b0 *
b0 )
b0 (
b0 '
b0 &
b0 %
0$
0#
0"
b0 !
$end
#5000
1"
#10000
0"
#15000
1"
#20000
12
1?
b111 E
b101 C
b100011 I
b100011 1
b101 .
b111 /
b10000000000000000000110011 0
1,
b10000000000000000000110011 %
b10000000000000000000110011 3
b111 *
b111 8
b101 (
b101 6
0"
b10000000000000000000110011 L
b111 K
b101 J
0-
#25000
b100011 H
b100011 ;
b111 D
b101 B
1"
#30000
0"
#35000
b100011 !
b100011 :
b100011 F
1"
#40000
0"
#45000
b100011 G
1"
#50000
b11 K
b11111111111111111111111111111000 J
0"
#55000
1"
#60000
b11 E
b11111111111111111111111111111000 C
b11111111111111111111111111101000 I
b1111111111111111111111111111111111111111111111111111111111101000 1
b11111111111111111111111111111000 .
b11 /
b11 *
b11 8
b11111111111111111111111111111000 (
b11111111111111111111111111111000 6
0"
#65000
b11111111111111111111111111101000 H
b11 D
b1011111111111111111111111111101000 ;
b11111111111111111111111111111000 B
1"
#70000
0"
#75000
b11111111111111111111111111101000 !
b11111111111111111111111111101000 :
b11111111111111111111111111101000 F
1"
#80000
0"
#85000
b11111111111111111111111111101000 G
1"
#90000
b10000000000001000000110011 L
0"
#95000
1"
#100000
b111111111111111111111111111111000 C
0?
1>
b11111111111111111111111111111111 I
b10000000000001000000110011 0
b10000000000001000000110011 %
b10000000000001000000110011 3
0"
#105000
b11111111111111111111111111111111 H
1A
b1111111111111111111111111111111111111111111111111111111111101000 ;
b111111111111111111111111111111000 B
1"
#110000
0"
#115000
b11111111111111111111111111111111 !
b11111111111111111111111111111111 :
b11111111111111111111111111111111 F
1"
#120000
0"
#125000
b11111111111111111111111111111111 G
1"
#130000
b10000000000010000000110011 L
0"
#135000
1"
#140000
0>
1=
b10 I
b1011111111111111111111111111101000 1
b10000000000010000000110011 0
b10000000000010000000110011 %
b10000000000010000000110011 3
0"
